{"2023":{"3":{"sleepIndex":83,"recoveryIndex":80.5,"movementIndex":73.5,"sleepTrackerMissingInfo":false,"contributorAverages":{"Restfulness":95,"HRV Form":83.66666666666667,"Timing":85.5,"Restorative Sleep":63.5,"HR Drop":55,"Steps":74.5,"Active Hours":46,"Activity":88.5,"Workout Frequency":99,"Sleep Quotient":83,"Movement Index":69.5,"Temperature":91.5,"Sleep Efficiency":70,"Resting Heart Rate":96}},"4":{"sleepIndex":82.5,"recoveryIndex":84.75,"movementIndex":63.75,"sleepTrackerMissingInfo":false,"contributorAverages":{"Restfulness":91.25,"Timing":79.5,"Restorative Sleep":81.75,"HR Drop":35.5,"Activity":90.75,"Active Hours":48.75,"Steps":46.75,"Workout Frequency":80.33333333333333,"HRV Form":90.66666666666667,"Temperature":97.5,"Sleep Quotient":82.5,"Movement Index":65.75,"Sleep Efficiency":80,"Resting Heart Rate":93}},"5":{"sleepIndex":78.6,"recoveryIndex":80.4,"movementIndex":67,"sleepTrackerMissingInfo":false,"contributorAverages":{"HRV Form":88.85714285714286,"Restfulness":84,"HR Drop":59,"Restorative Sleep":85,"Timing":87.8,"Sleep Efficiency":74.5,"Workout Frequency":87.8,"Steps":62.4,"Activity":89.5,"Active Hours":37.8,"Temperature":92,"Sleep Quotient":78.6,"Movement Index":67,"Resting Heart Rate":83.2,"Total Sleep":84,"Temperature Deviation":95.66666666666667}},"6":{"sleepIndex":68.25,"recoveryIndex":76,"movementIndex":73,"sleepTrackerMissingInfo":false,"contributorAverages":{"Restorative Sleep":84,"HR Drop":73.33333333333333,"Timing":59.5,"Total Sleep":80,"HRV Form":88.375,"Active Hours":58,"Steps":71.25,"Workout Frequency":87.75,"Activity":94.5,"Resting Heart Rate":82,"Temperature":96,"Sleep Quotient":68.25,"Movement Index":72.75,"Temperature Deviation":93,"Restfulness":83,"Sleep Efficiency":80}},"7":{"sleepIndex":69.2,"recoveryIndex":73.8,"movementIndex":70.2,"sleepTrackerMissingInfo":false,"contributorAverages":{"Restorative Sleep":78,"Timing":80.75,"Restfulness":82.25,"HR Drop":57.5,"Sleep Efficiency":75,"Activity":97.25,"Active Hours":73,"Steps":42.6,"Workout Frequency":86.2,"Sleep Quotient":68.25,"Resting Heart Rate":74.25,"HRV Form":85.2,"Temperature":95.4,"Total Sleep":79,"Movement Index":68.75,"Temperature Deviation":96}},"8":{"sleepIndex":70.25,"recoveryIndex":74.5,"movementIndex":64.75,"sleepTrackerMissingInfo":false,"contributorAverages":{"Restorative Sleep":87.33333333333333,"Total Sleep":82.33333333333333,"Timing":77.33333333333333,"Steps":17.25,"Activity":99,"Active Hours":91.5,"Movement Index":61,"Temperature":98.33333333333333,"Sleep Quotient":70.25,"HRV Form":86.2,"Resting Heart Rate":73.5,"Temperature Deviation":99.5,"HR Drop":58.666666666666664,"Restfulness":78,"Workout Frequency":60.666666666666664}},"9":{"sleepIndex":64.25,"recoveryIndex":58.5,"movementIndex":60.5,"sleepTrackerMissingInfo":true,"contributorAverages":{"Total Sleep":81,"HR Drop":74.5,"Timing":95,"Restorative Sleep":88,"Workout Frequency":55.666666666666664,"Steps":7,"Movement Index":57.5,"Sleep Quotient":86,"Resting Heart Rate":76,"HRV Form":80.5,"Temperature Deviation":99,"Active Hours":83,"Temperature":99}},"10":{"sleepIndex":13.6,"recoveryIndex":15.2,"movementIndex":11.8,"sleepTrackerMissingInfo":true,"contributorAverages":{"HRV Form":90.5,"HR Drop":72,"Timing":64,"Total Sleep":79,"Restorative Sleep":82,"Workout Frequency":49,"Steps":5,"Active Hours":92,"Activity":99,"Movement Index":58,"Sleep Quotient":68,"Resting Heart Rate":83,"Temperature":98}},"11":{"sleepIndex":21,"recoveryIndex":19.75,"movementIndex":14.75,"sleepTrackerMissingInfo":true,"contributorAverages":{}},"12":{"sleepIndex":82.66666666666667,"recoveryIndex":74.33333333333333,"movementIndex":55,"sleepTrackerMissingInfo":false,"contributorAverages":{"Timing":88.33333333333333,"HR Drop":71.33333333333333,"Total Sleep":92,"Restfulness":85,"Steps":2,"Workout Frequency":42.666666666666664,"Active Hours":82.33333333333333,"Resting Heart Rate":84.66666666666667,"Sleep Quotient":82.66666666666667,"HRV Form":76.6,"Movement Index":56,"Temperature Deviation":97,"Restorative Sleep":87,"Temperature":95}}},"latest":{"sleepIndex":82.66666666666667,"recoveryIndex":74.33333333333333,"movementIndex":55,"sleepTrackerMissingInfo":false,"contributorAverages":{"Timing":88.33333333333333,"HR Drop":71.33333333333333,"Total Sleep":92,"Restfulness":85,"Steps":2,"Workout Frequency":42.666666666666664,"Active Hours":82.33333333333333,"Resting Heart Rate":84.66666666666667,"Sleep Quotient":82.66666666666667,"HRV Form":76.6,"Movement Index":56,"Temperature Deviation":97,"Restorative Sleep":87,"Temperature":95}},"currentYear":2023,"currentMonth":12}